analytics/__init__.py
analytics/test_structure.py
analytics/points_per_drive/__init__.py
analytics/points_per_drive/calculator.py
analytics/points_per_drive/chart_renderer.py
analytics/points_per_drive/data_loader.py
analytics/points_per_drive/main.py
analytics/points_per_drive/models.py
analytics/shared/__init__.py
analytics/success_rate/__init__.py
analytics/success_rate/calculator.py
analytics/success_rate/chart_renderer.py
analytics/success_rate/data_loader.py
analytics/success_rate/main.py
analytics/success_rate/models.py
api_sports/api.py
api_sports/NBA/NBA_endpoints.py
api_sports/NFL/NFL_endpoints.py
api_sports/scripts/extract_games_teams_injuries.py
api_sports/scripts/extract_nfl_endpoints_data.py
cfd/__init__.py
cfd/client.py
cfd/extract_cfd_data.py
cfd/test_client.py
commonv2/__init__.py
commonv2/_data/__init__.py
commonv2/_data/adapters.py
commonv2/_data/database.py
commonv2/_data/loading_strategies.py
commonv2/_data/schema_detector.py
commonv2/_data/sql_queries.py
commonv2/core/__init__.py
commonv2/core/cli.py
commonv2/core/config.py
commonv2/core/errors.py
commonv2/core/logging.py
commonv2/domain/__init__.py
commonv2/domain/adapters.py
commonv2/domain/models.py
commonv2/domain/schedules.py
commonv2/domain/teams.py
commonv2/persistence/bucket_adapter.py
commonv2/utils/__init__.py
commonv2/utils/decorators.py
commonv2/utils/helpers.py
commonv2/utils/validation.py
commonv2/utils/checkpointing/__init__.py
commonv2/utils/checkpointing/manager.py
commonv2/utils/checkpointing/state.py
commonv2/utils/memory/__init__.py
commonv2/utils/memory/estimator.py
commonv2/utils/memory/manager.py
commonv2/utils/validation/__init__.py
commonv2/utils/validation/config.py
commonv2/utils/validation/core.py
espn_unofficial_api/ESPN_API_TESTCALL.py
nfl_data_wrapper/__init__.py
nfl_data_wrapper/extract_wrapper_data.py
nfl_data_wrapper/etl/__init__.py
nfl_data_wrapper/etl/extract/__init__.py
nfl_data_wrapper/etl/extract/api.py
nfl_data_wrapper/etl/extract/api_core.py
quantcup_backend-0.1.5.dist-info/METADATA
quantcup_backend-0.1.5.dist-info/WHEEL
quantcup_backend-0.1.5.dist-info/entry_points.txt
quantcup_backend-0.1.5.dist-info/top_level.txt
quantcup_backend-0.1.5.dist-info/RECORD
