Metadata-Version: 2.4
Name: quantcup-backend
Version: 0.1.5
Summary: QuantCup – unified CLI for sports analytics ecosystem
Requires-Python: >=3.8
Requires-Dist: typer>=0.12
Requires-Dist: pandas<2.4,>=2.2.3
Requires-Dist: sqlalchemy>=1.4.0
Requires-Dist: psycopg2-binary>=2.9.0
Requires-Dist: python-dotenv>=0.19.0
Requires-Dist: requests>=2.25.0
Requires-Dist: pydantic>=2.0.0
Requires-Dist: pydantic-settings>=2.0.0
Requires-Dist: nfl-data-py>=0.3.0
Requires-Dist: pytz>=2021.1
Requires-Dist: pytest>=7.0.0
Requires-Dist: httpx>=0.24.0
